simpleud/__init__.py
simpleud/uploader.py
simpleud-0.1.1.dist-info/licenses/LICENSE
simpleud-0.1.1.dist-info/METADATA
simpleud-0.1.1.dist-info/WHEEL
simpleud-0.1.1.dist-info/top_level.txt
simpleud-0.1.1.dist-info/RECORD
